atrax/Atrax.py
atrax/__init__.py
atrax/version.py
atrax/Dataset/__init__.py
atrax/Dataset/dataset.py
atrax/Dataset/group.py
atrax/Dataset/indexers.py
atrax/Series/__init__.py
atrax/Series/indexers.py
atrax/Series/series.py
atrax/utils/__init__.py
atrax/utils/date_accessor.py
atrax/utils/date_fns.py
atrax-0.0.33.dist-info/licenses/LICENSE
atrax-0.0.33.dist-info/METADATA
atrax-0.0.33.dist-info/WHEEL
atrax-0.0.33.dist-info/top_level.txt
atrax-0.0.33.dist-info/RECORD
