Metadata-Version: 2.4
Name: atrax
Version: 0.0.33
Summary: A pandas-like library for tabular and time series data.
Author-email: C5m7b4 <c5m7b4@gmail.com>
License: MIT
Project-URL: Homepage, https://github.com/C5m7b4/atrax
Project-URL: Issues, https://github.com/C5m7b4/atrax
Requires-Python: >=3.8
License-File: LICENSE
Requires-Dist: psycopg2
Requires-Dist: sqlalchemy
Provides-Extra: dev
Requires-Dist: pytest; extra == "dev"
Dynamic: license-file
